analyticalmachine/__init__.py
analyticalmachine-0.0.dist-info/METADATA
analyticalmachine-0.0.dist-info/WHEEL
analyticalmachine-0.0.dist-info/top_level.txt
analyticalmachine-0.0.dist-info/RECORD
