Metadata-Version: 2.1
Name: analyticalmachine
Version: 0.0
Summary: Python package for AnalyticalMachine.com
Home-page: UNKNOWN
Author: Prithvi Kambhampati & Sai Veena Katta
Author-email: kambhampati.prithvi@gmail.com
License: MIT
Platform: UNKNOWN
